tree_sitter_arkts/__init__.py
tree_sitter_arkts/__init__.pyi
tree_sitter_arkts/_binding.pyd
tree_sitter_arkts/binding.c
tree_sitter_arkts/py.typed
tree_sitter_arkts/queries/highlights.scm
tree_sitter_arkts/queries/tags.scm
tree_sitter_arkts_open-0.1.8.dist-info/METADATA
tree_sitter_arkts_open-0.1.8.dist-info/WHEEL
tree_sitter_arkts_open-0.1.8.dist-info/top_level.txt
tree_sitter_arkts_open-0.1.8.dist-info/RECORD
