Metadata-Version: 2.1
Name: tree-sitter-arkts-open
Version: 0.1.8
Summary: Tree-sitter grammar for ArkTS (HarmonyOS development language)
Author-email: million <liya941314@gmail.com>
License: MIT
Project-URL: Homepage, https://github.com/Million-mo/tree-sitter-arkts
Project-URL: Repository, https://github.com/Million-mo/tree-sitter-arkts
Project-URL: Issues, https://github.com/Million-mo/tree-sitter-arkts/issues
Keywords: incremental,parsing,tree-sitter,arkts,harmonyos,huawei
Classifier: Development Status :: 4 - Beta
Classifier: Intended Audience :: Developers
Classifier: License :: OSI Approved :: MIT License
Classifier: Programming Language :: Python :: 3
Classifier: Programming Language :: Python :: 3.10
Classifier: Programming Language :: Python :: 3.11
Classifier: Programming Language :: Python :: 3.12
Classifier: Topic :: Software Development :: Compilers
Classifier: Topic :: Text Processing :: Linguistic
Classifier: Typing :: Typed
Requires-Python: >=3.10
Requires-Dist: tree-sitter >=0.23.0
Provides-Extra: core
Requires-Dist: tree-sitter ~=0.24 ; extra == 'core'
